prview/__init__.py
prview/cli.py
prview/web/__init__.py
prview/web/server.py
prview/web/templates/index.html
prview/web/templates/settings.html
prview/web/templates/partials/prs.html
prview/web/templates/partials/status.html
prview-0.2.2.dist-info/METADATA
prview-0.2.2.dist-info/WHEEL
prview-0.2.2.dist-info/entry_points.txt
prview-0.2.2.dist-info/licenses/LICENSE
prview-0.2.2.dist-info/RECORD
