Metadata-Version: 2.4
Name: prview
Version: 0.2.2
Summary: Beautiful TUI and web dashboard for GitHub PRs and CI status
Project-URL: Homepage, https://github.com/aminghadersohi/prview
Project-URL: Repository, https://github.com/aminghadersohi/prview
Project-URL: Issues, https://github.com/aminghadersohi/prview/issues
Author-email: Amin Ghadersohi <amin.ghadersohi@gmail.com>
License-Expression: MIT
License-File: LICENSE
Keywords: ci,cli,dashboard,github,pull-request,review,tui
Classifier: Development Status :: 4 - Beta
Classifier: Environment :: Console
Classifier: Environment :: Web Environment
Classifier: Intended Audience :: Developers
Classifier: License :: OSI Approved :: MIT License
Classifier: Operating System :: OS Independent
Classifier: Programming Language :: Python :: 3
Classifier: Programming Language :: Python :: 3.9
Classifier: Programming Language :: Python :: 3.10
Classifier: Programming Language :: Python :: 3.11
Classifier: Programming Language :: Python :: 3.12
Classifier: Topic :: Software Development :: Version Control :: Git
Requires-Python: >=3.9
Requires-Dist: pyyaml>=6.0
Requires-Dist: rich>=13.0.0
Provides-Extra: all
Requires-Dist: fastapi>=0.100.0; extra == 'all'
Requires-Dist: jinja2>=3.0.0; extra == 'all'
Requires-Dist: pynput>=1.7.0; extra == 'all'
Requires-Dist: uvicorn>=0.23.0; extra == 'all'
Provides-Extra: keyboard
Requires-Dist: pynput>=1.7.0; extra == 'keyboard'
Provides-Extra: web
Requires-Dist: fastapi>=0.100.0; extra == 'web'
Requires-Dist: jinja2>=3.0.0; extra == 'web'
Requires-Dist: uvicorn>=0.23.0; extra == 'web'
